async_yandex_checkout/__init__.py
async_yandex_checkout/configuration.py
async_yandex_checkout/connector.py
async_yandex_checkout/payment.py
async_yandex_checkout-0.0.7.dist-info/LICENSE.txt
async_yandex_checkout-0.0.7.dist-info/METADATA
async_yandex_checkout-0.0.7.dist-info/WHEEL
async_yandex_checkout-0.0.7.dist-info/top_level.txt
async_yandex_checkout-0.0.7.dist-info/RECORD
