Metadata-Version: 2.1
Name: async-yandex-checkout
Version: 0.0.7
Summary: Yandex checkout async api wrapper
Home-page: https://github.com/yank0vy3rdna/async-yandex-checkout
Author: yank0vy3rdna
Author-email: yankovyerdna@yandex.ru
License: GPLv3
Platform: UNKNOWN
Classifier: Programming Language :: Python :: 3.6
Classifier: Programming Language :: Python :: 3.7
Classifier: Programming Language :: Python :: 3.8
Classifier: License :: OSI Approved :: GNU General Public License v3 or later (GPLv3+)
Classifier: Operating System :: OS Independent
Classifier: Intended Audience :: Developers
Classifier: Natural Language :: English
Requires-Python: >=3.6
Requires-Dist: aiohttp (>=3.6)
Provides-Extra: ujson
